README.rst
setup.py
src/close/__init__.py
src/close.consumer.egg-info/PKG-INFO
src/close.consumer.egg-info/SOURCES.txt
src/close.consumer.egg-info/dependency_links.txt
src/close.consumer.egg-info/entry_points.txt
src/close.consumer.egg-info/namespace_packages.txt
src/close.consumer.egg-info/not-zip-safe
src/close.consumer.egg-info/requires.txt
src/close.consumer.egg-info/top_level.txt
src/close/consumer/__init__.py
src/close/consumer/base.py
src/close/consumer/consumer.py
src/close/consumer/parse.py
src/close/consumer/process.py
src/close/consumer/utils.py