Metadata-Version: 1.0
Name: close.consumer
Version: 0.2.1
Summary: gevent based Streaming API consumer
Home-page: http://github.com/thruflo/close.consumer
Author: James Arthur
Author-email: thruflo@googlemail.com
License: Creative Commons CC0 1.0 Universal
Platform: UNKNOWN
Classifier: Development Status :: 3 - Alpha
Classifier: Environment :: Web Environment
Classifier: Intended Audience :: Developers
Classifier: License :: Public Domain
Classifier: Programming Language :: Python
